Workbook

Sheet Identity
A1: field | B1: value | C1: unit
A2: schemaVersion | B2: 1.0
A3: id | B3: P01
A4: name | B4: Almonte Solar
A5: location.country | B5: Spain
A6: location.countryCode | B6: ES
A7: location.iso3 | B7: ESP
A8: location.lat | B8: 39.25 | C8: degrees
A9: location.lon | B9: -6.52 | C9: degrees
A10: asset.technology | B10: solar
A11: asset.stage | B11: ready_to_build
A12: asset.capacityMw | B12: 180 | C12: MW
A13: asset.codYear | B13: 2028 | C13: year
A14: asset.netCapacityFactor | B14: 0.230324 | C14: fraction
A15: asset.opexPerKwYear | B15: 12.813182 | C15: EUR/kW/yr
A16: revenue.ppaShare | B16: 0.55 | C16: fraction
A17: revenue.ppaPrice | B17: 34 | C17: EUR/MWh
A18: revenue.ppaTenorYears | B18: 10 | C18: years
A19: revenue.countryBaseloadPrice | B19: 58 | C19: EUR/MWh
A20: revenue.captureFactor | B20: 0.68 | C20: fraction
A21: execution.developmentRiskScore | B21: 2.7 | C21: 1.0-5.0
A22: execution.gridSecured | B22: TRUE
A23: execution.omContracted | B23: TRUE
A24: execution.currency | B24: EUR
A25: capitalStructure.totalCapex | B25: 103.32256 | C25: EURm
A26: capitalStructure.seniorDebt | B26: 74.392246 | C26: EURm
A27: capitalStructure.maxGearing | B27: 0.72 | C27: fraction

Sheet Assumptions
A1: field | B1: value | C1: unit
A2: assumptions.baseYear | B2: 2027 | C2: year
A3: assumptions.taxRate | B3: 0.2 | C3: fraction
A4: assumptions.depreciationYears | B4: 25 | C4: years
A5: assumptions.debtRate | B5: 0.055 | C5: fraction
A6: assumptions.debtTenorYears | B6: 18 | C6: years
A8: Declared inputs, not configuration. The loader's dispersion report compares these across the pipeline.

Sheet Provenance
A1: group | B1: estimateBasis | C1: confidence | D1: note
A2: provenance.preparedBy | B2: iberia.origination@meridiancapital.example
A3: provenance.preparedOn | B3: 2026-08-14
A4: provenance.modelVersion | B4: almonte-rtb-v4
A5: per field group
A6: generation | B6: engineering_estimate | C6: high | D6: P50 from a third-party yield study, two years of on-site pyranometer data.
A7: price | B7: contracted | C7: high | D7: 55% under a signed 10-year PPA; merchant tail from the house Iberian curve.
A8: capex | B8: binding_offer | C8: medium | D8: EPC offer valid to 2027-03; BoP and grid works at engineering estimate.
A9: opex | B9: benchmark | C9: medium | D9: Iberian utility-scale PV benchmark, adjusted for single-axis tracking.
A10: debtTerms | B10: binding_offer | C10: medium | D10: Indicative term sheet from two lenders; margin not yet fixed.
A11: grid | B11: contracted | C11: high | D11: Firm connection agreement signed 2025-11.
A12: om | B12: contracted | C12: high | D12: Ten-year full-scope O&M agreement signed with the EPC contractor.
A14: estimateBasis: contracted | binding_offer | engineering_estimate | benchmark | internal_model | placeholder. confidence: high | medium | low. Reported, never blocking.

Sheet Statements
A1: field | B1: unit | C1: 2027 | D1: 2028 | E1: 2029 | F1: 2030 | G1: 2031 | H1: 2032 | I1: 2033 | J1: 2034 | K1: 2035 | L1: 2036 | M1: 2037 | N1: 2038 | O1: 2039 | P1: 2040 | Q1: 2041 | R1: 2042 | S1: 2043 | T1: 2044 | U1: 2045 | V1: 2046 | W1: 2047 | X1: 2048 | Y1: 2049 | Z1: 2050 | AA1: 2051 | AB1: 2052 | AC1: 2053 | AD1: 2054 | AE1: 2055 | AF1: 2056
A2: physicals
A3: physicals.generationGwh | B3: GWh | C3: 0 | D3: 199.74624 | E3: 361.3591 | F3: 359.55231 | G3: 357.75455 | H3: 355.96577 | I3: 354.18594 | J3: 352.41501 | K3: 350.65294 | L3: 348.89967 | M3: 347.15518 | N3: 345.4194 | O3: 343.6923 | P3: 341.97384 | Q3: 340.26397 | R3: 338.56265 | S3: 336.86984 | T3: 335.18549 | U3: 333.50956 | V3: 331.84202 | W3: 330.1828 | X3: 328.53189 | Y3: 326.88923 | Z3: 325.25479 | AA3: 323.62851 | AB3: 322.01037 | AC3: 320.40032 | AD3: 318.79832 | AE3: 317.20432 | AF3: 315.6183
A4: physicals.achievedPrice | B4: EUR/MWh | C4: 0 | D4: 36.25 | E4: 36.71205 | F4: 37.182307 | G4: 37.660936 | H4: 38.148105 | I4: 38.643986 | J4: 39.148755 | K4: 39.66259 | L4: 40.185674 | M4: 40.718193 | N4: 48.00893 | O4: 49.017118 | P4: 50.046477 | Q4: 51.097453 | R4: 52.1705 | S4: 53.26608 | T4: 54.384668 | U4: 55.526746 | V4: 56.692808 | W4: 57.883356 | X4: 59.098907 | Y4: 60.339984 | Z4: 61.607124 | AA4: 62.900873 | AB4: 64.221792 | AC4: 65.570449 | AD4: 66.947429 | AE4: 68.353325 | AF4: 69.788745
A5: incomeStatement
A6: incomeStatement.revenue | B6: EURm | C6: 0 | D6: 7.240801 | E6: 13.266233 | F6: 13.368984 | G6: 13.473371 | H6: 13.57942 | I6: 13.687157 | J6: 13.796609 | K6: 13.907804 | L6: 14.020768 | M6: 14.135532 | N6: 16.583216 | O6: 16.846806 | P6: 17.114586 | Q6: 17.386622 | R6: 17.662983 | S6: 17.943736 | T6: 18.228952 | U6: 18.518701 | V6: 18.813055 | W6: 19.112089 | X6: 19.415876 | Y6: 19.724491 | Z6: 20.038012 | AA6: 20.356516 | AB6: 20.680083 | AC6: 21.008793 | AD6: 21.342727 | AE6: 21.68197 | AF6: 22.026605
A7: incomeStatement.opex | B7: EURm | C7: 0 | D7: 2.306373 | E7: 2.354807 | F7: 2.404258 | G7: 2.454747 | H7: 2.506297 | I7: 2.558929 | J7: 2.612666 | K7: 2.667532 | L7: 2.723551 | M7: 2.780745 | N7: 2.839141 | O7: 2.898763 | P7: 2.959637 | Q7: 3.021789 | R7: 3.085247 | S7: 3.150037 | T7: 3.216188 | U7: 3.283728 | V7: 3.352686 | W7: 3.423092 | X7: 3.494977 | Y7: 3.568372 | Z7: 3.643308 | AA7: 3.719817 | AB7: 3.797933 | AC7: 3.87769 | AD7: 3.959121 | AE7: 4.042263 | AF7: 4.12715
A8: incomeStatement.ebitda | B8: EURm | C8: 0 | D8: 4.934428 | E8: 10.911427 | F8: 10.964727 | G8: 11.018624 | H8: 11.073123 | I8: 11.128228 | J8: 11.183943 | K8: 11.240271 | L8: 11.297218 | M8: 11.354786 | N8: 13.744075 | O8: 13.948043 | P8: 14.154949 | Q8: 14.364833 | R8: 14.577736 | S8: 14.793699 | T8: 15.012764 | U8: 15.234973 | V8: 15.46037 | W8: 15.688997 | X8: 15.920898 | Y8: 16.156119 | Z8: 16.394704 | AA8: 16.636699 | AB8: 16.88215 | AC8: 17.131103 | AD8: 17.383606 | AE8: 17.639707 | AF8: 17.899455
A9: incomeStatement.depreciation | B9: EURm | C9: 0 | D9: 4.132903 | E9: 4.132903 | F9: 4.132903 | G9: 4.132903 | H9: 4.132903 | I9: 4.132903 | J9: 4.132903 | K9: 4.132903 | L9: 4.132903 | M9: 4.132903 | N9: 4.132903 | O9: 4.132903 | P9: 4.132903 | Q9: 4.132903 | R9: 4.132903 | S9: 4.132903 | T9: 4.132903 | U9: 4.132903 | V9: 4.132903 | W9: 4.132903 | X9: 4.132903 | Y9: 4.132903 | Z9: 4.132903 | AA9: 4.132903 | AB9: 4.132903 | AC9: 0 | AD9: 0 | AE9: 0 | AF9: 0
A10: incomeStatement.ebit | B10: EURm | C10: 0 | D10: 0.801526 | E10: 6.778524 | F10: 6.831824 | G10: 6.885722 | H10: 6.940221 | I10: 6.995325 | J10: 7.05104 | K10: 7.107369 | L10: 7.164315 | M10: 7.221884 | N10: 9.611172 | O10: 9.815141 | P10: 10.022047 | Q10: 10.231931 | R10: 10.444833 | S10: 10.660796 | T10: 10.879861 | U10: 11.102071 | V10: 11.327467 | W10: 11.556094 | X10: 11.787996 | Y10: 12.023217 | Z10: 12.261802 | AA10: 12.503796 | AB10: 12.749247 | AC10: 17.131103 | AD10: 17.383606 | AE10: 17.639707 | AF10: 17.899455
A11: incomeStatement.interestExpense | B11: EURm | C11: 0 | D11: 4.091574 | E11: 3.952788 | F11: 3.806369 | G11: 3.651897 | H11: 3.488928 | I11: 3.316997 | J11: 3.13561 | K11: 2.944246 | L11: 2.742357 | M11: 2.529364 | N11: 2.304657 | O11: 2.067591 | P11: 1.817486 | Q11: 1.553625 | R11: 1.275252 | S11: 0.981569 | T11: 0.671732 | U11: 0.344855 | V11: 0 | W11: 0 | X11: 0 | Y11: 0 | Z11: 0 | AA11: 0 | AB11: 0 | AC11: 0 | AD11: 0 | AE11: 0 | AF11: 0
A12: incomeStatement.pbt | B12: EURm | C12: 0 | D12: -3.290048 | E12: 2.825737 | F12: 3.025456 | G12: 3.233825 | H12: 3.451292 | I12: 3.678328 | J12: 3.91543 | K12: 4.163123 | L12: 4.421958 | M12: 4.69252 | N12: 7.306516 | O12: 7.74755 | P12: 8.204561 | Q12: 8.678306 | R12: 9.169581 | S12: 9.679228 | T12: 10.208129 | U12: 10.757215 | V12: 11.327467 | W12: 11.556094 | X12: 11.787996 | Y12: 12.023217 | Z12: 12.261802 | AA12: 12.503796 | AB12: 12.749247 | AC12: 17.131103 | AD12: 17.383606 | AE12: 17.639707 | AF12: 17.899455
A13: incomeStatement.taxExpense | B13: EURm | C13: 0 | D13: 0 | E13: 0.565147 | F13: 0.605091 | G13: 0.646765 | H13: 0.690258 | I13: 0.735666 | J13: 0.783086 | K13: 0.832625 | L13: 0.884392 | M13: 0.938504 | N13: 1.461303 | O13: 1.54951 | P13: 1.640912 | Q13: 1.735661 | R13: 1.833916 | S13: 1.935846 | T13: 2.041626 | U13: 2.151443 | V13: 2.265493 | W13: 2.311219 | X13: 2.357599 | Y13: 2.404643 | Z13: 2.45236 | AA13: 2.500759 | AB13: 2.549849 | AC13: 3.426221 | AD13: 3.476721 | AE13: 3.527941 | AF13: 3.579891
A14: incomeStatement.netIncome | B14: EURm | C14: 0 | D14: -3.290048 | E14: 2.260589 | F14: 2.420364 | G14: 2.58706 | H14: 2.761034 | I14: 2.942663 | J14: 3.132344 | K14: 3.330498 | L14: 3.537567 | M14: 3.754016 | N14: 5.845213 | O14: 6.19804 | P14: 6.563649 | Q14: 6.942645 | R14: 7.335665 | S14: 7.743382 | T14: 8.166503 | U14: 8.605772 | V14: 9.061974 | W14: 9.244875 | X14: 9.430397 | Y14: 9.618573 | Z14: 9.809441 | AA14: 10.003037 | AB14: 10.199398 | AC14: 13.704882 | AD14: 13.906885 | AE14: 14.111766 | AF14: 14.319564
A15: cashFlow
A16: cashFlow.interestPaid | B16: EURm | C16: 0 | D16: 4.091574 | E16: 3.952788 | F16: 3.806369 | G16: 3.651897 | H16: 3.488928 | I16: 3.316997 | J16: 3.13561 | K16: 2.944246 | L16: 2.742357 | M16: 2.529364 | N16: 2.304657 | O16: 2.067591 | P16: 1.817486 | Q16: 1.553625 | R16: 1.275252 | S16: 0.981569 | T16: 0.671732 | U16: 0.344855 | V16: 0 | W16: 0 | X16: 0 | Y16: 0 | Z16: 0 | AA16: 0 | AB16: 0 | AC16: 0 | AD16: 0 | AE16: 0 | AF16: 0
A17: cashFlow.debtRepayment | B17: EURm | C17: 0 | D17: 2.523379 | E17: 2.662165 | F17: 2.808584 | G17: 2.963056 | H17: 3.126024 | I17: 3.297955 | J17: 3.479343 | K17: 3.670706 | L17: 3.872595 | M17: 4.085588 | N17: 4.310295 | O17: 4.547362 | P17: 4.797467 | Q17: 5.061327 | R17: 5.3397 | S17: 5.633384 | T17: 5.94322 | U17: 6.270097 | V17: 0 | W17: 0 | X17: 0 | Y17: 0 | Z17: 0 | AA17: 0 | AB17: 0 | AC17: 0 | AD17: 0 | AE17: 0 | AF17: 0
A18: cashFlow.taxPaid | B18: EURm | C18: 0 | D18: 0 | E18: 0.565147 | F18: 0.605091 | G18: 0.646765 | H18: 0.690258 | I18: 0.735666 | J18: 0.783086 | K18: 0.832625 | L18: 0.884392 | M18: 0.938504 | N18: 1.461303 | O18: 1.54951 | P18: 1.640912 | Q18: 1.735661 | R18: 1.833916 | S18: 1.935846 | T18: 2.041626 | U18: 2.151443 | V18: 2.265493 | W18: 2.311219 | X18: 2.357599 | Y18: 2.404643 | Z18: 2.45236 | AA18: 2.500759 | AB18: 2.549849 | AC18: 3.426221 | AD18: 3.476721 | AE18: 3.527941 | AF18: 3.579891
A19: cashFlow.capex | B19: EURm | C19: 28.930318 | D19: 74.392246 | E19: 0 | F19: 0 | G19: 0 | H19: 0 | I19: 0 | J19: 0 | K19: 0 | L19: 0 | M19: 0 | N19: 0 | O19: 0 | P19: 0 | Q19: 0 | R19: 0 | S19: 0 | T19: 0 | U19: 0 | V19: 0 | W19: 0 | X19: 0 | Y19: 0 | Z19: 0 | AA19: 0 | AB19: 0 | AC19: 0 | AD19: 0 | AE19: 0 | AF19: 0
A20: cashFlow.debtDrawdown | B20: EURm | C20: 0 | D20: 74.392246 | E20: 0 | F20: 0 | G20: 0 | H20: 0 | I20: 0 | J20: 0 | K20: 0 | L20: 0 | M20: 0 | N20: 0 | O20: 0 | P20: 0 | Q20: 0 | R20: 0 | S20: 0 | T20: 0 | U20: 0 | V20: 0 | W20: 0 | X20: 0 | Y20: 0 | Z20: 0 | AA20: 0 | AB20: 0 | AC20: 0 | AD20: 0 | AE20: 0 | AF20: 0
A21: cashFlow.equityDrawdown | B21: EURm | C21: 28.930318 | D21: 0 | E21: 0 | F21: 0 | G21: 0 | H21: 0 | I21: 0 | J21: 0 | K21: 0 | L21: 0 | M21: 0 | N21: 0 | O21: 0 | P21: 0 | Q21: 0 | R21: 0 | S21: 0 | T21: 0 | U21: 0 | V21: 0 | W21: 0 | X21: 0 | Y21: 0 | Z21: 0 | AA21: 0 | AB21: 0 | AC21: 0 | AD21: 0 | AE21: 0 | AF21: 0
A22: cashFlow.fcfe | B22: EURm | C22: -28.930318 | D22: -1.680524 | E22: 3.731327 | F22: 3.744683 | G22: 3.756907 | H22: 3.767912 | I22: 3.77761 | J22: 3.785904 | K22: 3.792694 | L22: 3.797874 | M22: 3.80133 | N22: 5.66782 | O22: 5.783581 | P22: 5.899085 | Q22: 6.01422 | R22: 6.128867 | S22: 6.242901 | T22: 6.356186 | U22: 6.468578 | V22: 13.194876 | W22: 13.377778 | X22: 13.563299 | Y22: 13.751476 | Z22: 13.942344 | AA22: 14.13594 | AB22: 14.3323 | AC22: 13.704882 | AD22: 13.906885 | AE22: 14.111766 | AF22: 14.319564
A23: debtSchedule
A24: debtSchedule.opening | B24: EURm | C24: 0 | D24: 0 | E24: 71.868867 | F24: 69.206702 | G24: 66.398119 | H24: 63.435063 | I24: 60.309039 | J24: 57.011084 | K24: 53.531741 | L24: 49.861035 | M24: 45.98844 | N24: 41.902852 | O24: 37.592556 | P24: 33.045194 | Q24: 28.247728 | R24: 23.186401 | S24: 17.8467 | T24: 12.213317 | U24: 6.270097 | V24: 0 | W24: 0 | X24: 0 | Y24: 0 | Z24: 0 | AA24: 0 | AB24: 0 | AC24: 0 | AD24: 0 | AE24: 0 | AF24: 0
A25: debtSchedule.drawdown | B25: EURm | C25: 0 | D25: 74.392246 | E25: 0 | F25: 0 | G25: 0 | H25: 0 | I25: 0 | J25: 0 | K25: 0 | L25: 0 | M25: 0 | N25: 0 | O25: 0 | P25: 0 | Q25: 0 | R25: 0 | S25: 0 | T25: 0 | U25: 0 | V25: 0 | W25: 0 | X25: 0 | Y25: 0 | Z25: 0 | AA25: 0 | AB25: 0 | AC25: 0 | AD25: 0 | AE25: 0 | AF25: 0
A26: debtSchedule.repayment | B26: EURm | C26: 0 | D26: 2.523379 | E26: 2.662165 | F26: 2.808584 | G26: 2.963056 | H26: 3.126024 | I26: 3.297955 | J26: 3.479343 | K26: 3.670706 | L26: 3.872595 | M26: 4.085588 | N26: 4.310295 | O26: 4.547362 | P26: 4.797467 | Q26: 5.061327 | R26: 5.3397 | S26: 5.633384 | T26: 5.94322 | U26: 6.270097 | V26: 0 | W26: 0 | X26: 0 | Y26: 0 | Z26: 0 | AA26: 0 | AB26: 0 | AC26: 0 | AD26: 0 | AE26: 0 | AF26: 0
A27: debtSchedule.closing | B27: EURm | C27: 0 | D27: 71.868867 | E27: 69.206702 | F27: 66.398119 | G27: 63.435063 | H27: 60.309039 | I27: 57.011084 | J27: 53.531741 | K27: 49.861035 | L27: 45.98844 | M27: 41.902852 | N27: 37.592556 | O27: 33.045194 | P27: 28.247728 | Q27: 23.186401 | R27: 17.8467 | S27: 12.213317 | T27: 6.270097 | U27: 0 | V27: 0 | W27: 0 | X27: 0 | Y27: 0 | Z27: 0 | AA27: 0 | AB27: 0 | AC27: 0 | AD27: 0 | AE27: 0 | AF27: 0
A28: balanceSheet
A29: balanceSheet.ppe | B29: EURm | C29: 28.930318 | D29: 99.189661 | E29: 95.056758 | F29: 90.923856 | G29: 86.790953 | H29: 82.658051 | I29: 78.525148 | J29: 74.392246 | K29: 70.259343 | L29: 66.126441 | M29: 61.993538 | N29: 57.860635 | O29: 53.727733 | P29: 49.59483 | Q29: 45.461928 | R29: 41.329025 | S29: 37.196123 | T29: 33.06322 | U29: 28.930318 | V29: 24.797415 | W29: 20.664513 | X29: 16.53161 | Y29: 12.398708 | Z29: 8.265805 | AA29: 4.132903 | AB29: 0 | AC29: 0 | AD29: 0 | AE29: 0 | AF29: 0
A30: ratios
A31: ratios.dscr | B31: x | D31: 0.745951 | E31: 1.64951 | F31: 1.657567 | G31: 1.665715 | H31: 1.673954 | I31: 1.682284 | J31: 1.690706 | K31: 1.699222 | L31: 1.707831 | M31: 1.716533 | N31: 2.077729 | O31: 2.108563 | P31: 2.139841 | Q31: 2.17157 | R31: 2.203755 | S31: 2.236403 | T31: 2.26952 | U31: 2.303112
A33: An empty dscr cell means null: dscr is defined only inside the debt life. Every other cell is a number.

Sheet TieOuts
A1: check | B1: max breach | C1: status | D1: 2027 | E1: 2028 | F1: 2029 | G1: 2030 | H1: 2031 | I1: 2032 | J1: 2033 | K1: 2034 | L1: 2035 | M1: 2036 | N1: 2037 | O1: 2038 | P1: 2039 | Q1: 2040 | R1: 2041 | S1: 2042 | T1: 2043 | U1: 2044 | V1: 2045 | W1: 2046 | X1: 2047 | Y1: 2048 | Z1: 2049 | AA1: 2050 | AB1: 2051 | AC1: 2052 | AD1: 2053 | AE1: 2054 | AF1: 2055 | AG1: 2056
A2: ebitda = revenue - opex | B2: =MAX(D2:AG2) | C2: =IF(B2=0,"PASS","FAIL") | D2: =MAX(0,ABS(Statements!C8-(Statements!C6-Statements!C7))-MAX(0.01,0.001*ABS(Statements!C8))) | E2: =MAX(0,ABS(Statements!D8-(Statements!D6-Statements!D7))-MAX(0.01,0.001*ABS(Statements!D8))) | F2: =MAX(0,ABS(Statements!E8-(Statements!E6-Statements!E7))-MAX(0.01,0.001*ABS(Statements!E8))) | G2: =MAX(0,ABS(Statements!F8-(Statements!F6-Statements!F7))-MAX(0.01,0.001*ABS(Statements!F8))) | H2: =MAX(0,ABS(Statements!G8-(Statements!G6-Statements!G7))-MAX(0.01,0.001*ABS(Statements!G8))) | I2: =MAX(0,ABS(Statements!H8-(Statements!H6-Statements!H7))-MAX(0.01,0.001*ABS(Statements!H8))) | J2: =MAX(0,ABS(Statements!I8-(Statements!I6-Statements!I7))-MAX(0.01,0.001*ABS(Statements!I8))) | K2: =MAX(0,ABS(Statements!J8-(Statements!J6-Statements!J7))-MAX(0.01,0.001*ABS(Statements!J8))) | ... AG2: =MAX(0,ABS(Statements!AF8-(Statements!AF6-Statements!AF7))-MAX(0.01,0.001*ABS(Statements!AF8)))
A3: ebit = ebitda - depreciation | B3: =MAX(D3:AG3) | C3: =IF(B3=0,"PASS","FAIL") | D3: =MAX(0,ABS(Statements!C10-(Statements!C8-Statements!C9))-MAX(0.01,0.001*ABS(Statements!C10))) | E3: =MAX(0,ABS(Statements!D10-(Statements!D8-Statements!D9))-MAX(0.01,0.001*ABS(Statements!D10))) | F3: =MAX(0,ABS(Statements!E10-(Statements!E8-Statements!E9))-MAX(0.01,0.001*ABS(Statements!E10))) | G3: =MAX(0,ABS(Statements!F10-(Statements!F8-Statements!F9))-MAX(0.01,0.001*ABS(Statements!F10))) | H3: =MAX(0,ABS(Statements!G10-(Statements!G8-Statements!G9))-MAX(0.01,0.001*ABS(Statements!G10))) | I3: =MAX(0,ABS(Statements!H10-(Statements!H8-Statements!H9))-MAX(0.01,0.001*ABS(Statements!H10))) | J3: =MAX(0,ABS(Statements!I10-(Statements!I8-Statements!I9))-MAX(0.01,0.001*ABS(Statements!I10))) | K3: =MAX(0,ABS(Statements!J10-(Statements!J8-Statements!J9))-MAX(0.01,0.001*ABS(Statements!J10))) | ... AG3: =MAX(0,ABS(Statements!AF10-(Statements!AF8-Statements!AF9))-MAX(0.01,0.001*ABS(Statements!AF10)))
A4: pbt = ebit - interestExpense | B4: =MAX(D4:AG4) | C4: =IF(B4=0,"PASS","FAIL") | D4: =MAX(0,ABS(Statements!C12-(Statements!C10-Statements!C11))-MAX(0.01,0.001*ABS(Statements!C12))) | E4: =MAX(0,ABS(Statements!D12-(Statements!D10-Statements!D11))-MAX(0.01,0.001*ABS(Statements!D12))) | F4: =MAX(0,ABS(Statements!E12-(Statements!E10-Statements!E11))-MAX(0.01,0.001*ABS(Statements!E12))) | G4: =MAX(0,ABS(Statements!F12-(Statements!F10-Statements!F11))-MAX(0.01,0.001*ABS(Statements!F12))) | H4: =MAX(0,ABS(Statements!G12-(Statements!G10-Statements!G11))-MAX(0.01,0.001*ABS(Statements!G12))) | I4: =MAX(0,ABS(Statements!H12-(Statements!H10-Statements!H11))-MAX(0.01,0.001*ABS(Statements!H12))) | J4: =MAX(0,ABS(Statements!I12-(Statements!I10-Statements!I11))-MAX(0.01,0.001*ABS(Statements!I12))) | K4: =MAX(0,ABS(Statements!J12-(Statements!J10-Statements!J11))-MAX(0.01,0.001*ABS(Statements!J12))) | ... AG4: =MAX(0,ABS(Statements!AF12-(Statements!AF10-Statements!AF11))-MAX(0.01,0.001*ABS(Statements!AF12)))
A5: netIncome = pbt - taxExpense | B5: =MAX(D5:AG5) | C5: =IF(B5=0,"PASS","FAIL") | D5: =MAX(0,ABS(Statements!C14-(Statements!C12-Statements!C13))-MAX(0.01,0.001*ABS(Statements!C14))) | E5: =MAX(0,ABS(Statements!D14-(Statements!D12-Statements!D13))-MAX(0.01,0.001*ABS(Statements!D14))) | F5: =MAX(0,ABS(Statements!E14-(Statements!E12-Statements!E13))-MAX(0.01,0.001*ABS(Statements!E14))) | G5: =MAX(0,ABS(Statements!F14-(Statements!F12-Statements!F13))-MAX(0.01,0.001*ABS(Statements!F14))) | H5: =MAX(0,ABS(Statements!G14-(Statements!G12-Statements!G13))-MAX(0.01,0.001*ABS(Statements!G14))) | I5: =MAX(0,ABS(Statements!H14-(Statements!H12-Statements!H13))-MAX(0.01,0.001*ABS(Statements!H14))) | J5: =MAX(0,ABS(Statements!I14-(Statements!I12-Statements!I13))-MAX(0.01,0.001*ABS(Statements!I14))) | K5: =MAX(0,ABS(Statements!J14-(Statements!J12-Statements!J13))-MAX(0.01,0.001*ABS(Statements!J14))) | ... AG5: =MAX(0,ABS(Statements!AF14-(Statements!AF12-Statements!AF13))-MAX(0.01,0.001*ABS(Statements!AF14)))
A6: revenue = generationGwh * 1000 * achievedPrice / 1e6 | B6: =MAX(D6:AG6) | C6: =IF(B6=0,"PASS","FAIL") | D6: =MAX(0,ABS(Statements!C6-Statements!C3*1000*Statements!C4/1000000)-MAX(0.01,0.001*ABS(Statements!C6))) | E6: =MAX(0,ABS(Statements!D6-Statements!D3*1000*Statements!D4/1000000)-MAX(0.01,0.001*ABS(Statements!D6))) | F6: =MAX(0,ABS(Statements!E6-Statements!E3*1000*Statements!E4/1000000)-MAX(0.01,0.001*ABS(Statements!E6))) | G6: =MAX(0,ABS(Statements!F6-Statements!F3*1000*Statements!F4/1000000)-MAX(0.01,0.001*ABS(Statements!F6))) | H6: =MAX(0,ABS(Statements!G6-Statements!G3*1000*Statements!G4/1000000)-MAX(0.01,0.001*ABS(Statements!G6))) | I6: =MAX(0,ABS(Statements!H6-Statements!H3*1000*Statements!H4/1000000)-MAX(0.01,0.001*ABS(Statements!H6))) | J6: =MAX(0,ABS(Statements!I6-Statements!I3*1000*Statements!I4/1000000)-MAX(0.01,0.001*ABS(Statements!I6))) | K6: =MAX(0,ABS(Statements!J6-Statements!J3*1000*Statements!J4/1000000)-MAX(0.01,0.001*ABS(Statements!J6))) | ... AG6: =MAX(0,ABS(Statements!AF6-Statements!AF3*1000*Statements!AF4/1000000)-MAX(0.01,0.001*ABS(Statements!AF6)))
A7: fcfe = ebitda - interestPaid - debtRepayment - taxPaid - capex + debtDrawdown | B7: =MAX(D7:AG7) | C7: =IF(B7=0,"PASS","FAIL") | D7: =MAX(0,ABS(Statements!C22-(Statements!C8-Statements!C16-Statements!C17-Statements!C18-Statements!C19+Statements!C20))-MAX(0.01,0.001*ABS(Statements!C22))) | E7: =MAX(0,ABS(Statements!D22-(Statements!D8-Statements!D16-Statements!D17-Statements!D18-Statements!D19+Statements!D20))-MAX(0.01,0.001*ABS(Statements!D22))) | F7: =MAX(0,ABS(Statements!E22-(Statements!E8-Statements!E16-Statements!E17-Statements!E18-Statements!E19+Statements!E20))-MAX(0.01,0.001*ABS(Statements!E22))) | G7: =MAX(0,ABS(Statements!F22-(Statements!F8-Statements!F16-Statements!F17-Statements!F18-Statements!F19+Statements!F20))-MAX(0.01,0.001*ABS(Statements!F22))) | H7: =MAX(0,ABS(Statements!G22-(Statements!G8-Statements!G16-Statements!G17-Statements!G18-Statements!G19+Statements!G20))-MAX(0.01,0.001*ABS(Statements!G22))) | I7: =MAX(0,ABS(Statements!H22-(Statements!H8-Statements!H16-Statements!H17-Statements!H18-Statements!H19+Statements!H20))-MAX(0.01,0.001*ABS(Statements!H22))) | J7: =MAX(0,ABS(Statements!I22-(Statements!I8-Statements!I16-Statements!I17-Statements!I18-Statements!I19+Statements!I20))-MAX(0.01,0.001*ABS(Statements!I22))) | K7: =MAX(0,ABS(Statements!J22-(Statements!J8-Statements!J16-Statements!J17-Statements!J18-Statements!J19+Statements!J20))-MAX(0.01,0.001*ABS(Statements!J22))) | ... AG7: =MAX(0,ABS(Statements!AF22-(Statements!AF8-Statements!AF16-Statements!AF17-Statements!AF18-Statements!AF19+Statements!AF20))-MAX(0.01,0.001*ABS(Statements!AF22)))
A8: closing = opening - repayment + drawdown | B8: =MAX(D8:AG8) | C8: =IF(B8=0,"PASS","FAIL") | D8: =MAX(0,ABS(Statements!C27-(Statements!C24-Statements!C26+Statements!C25))-MAX(0.01,0.001*ABS(Statements!C27))) | E8: =MAX(0,ABS(Statements!D27-(Statements!D24-Statements!D26+Statements!D25))-MAX(0.01,0.001*ABS(Statements!D27))) | F8: =MAX(0,ABS(Statements!E27-(Statements!E24-Statements!E26+Statements!E25))-MAX(0.01,0.001*ABS(Statements!E27))) | G8: =MAX(0,ABS(Statements!F27-(Statements!F24-Statements!F26+Statements!F25))-MAX(0.01,0.001*ABS(Statements!F27))) | H8: =MAX(0,ABS(Statements!G27-(Statements!G24-Statements!G26+Statements!G25))-MAX(0.01,0.001*ABS(Statements!G27))) | I8: =MAX(0,ABS(Statements!H27-(Statements!H24-Statements!H26+Statements!H25))-MAX(0.01,0.001*ABS(Statements!H27))) | J8: =MAX(0,ABS(Statements!I27-(Statements!I24-Statements!I26+Statements!I25))-MAX(0.01,0.001*ABS(Statements!I27))) | K8: =MAX(0,ABS(Statements!J27-(Statements!J24-Statements!J26+Statements!J25))-MAX(0.01,0.001*ABS(Statements!J27))) | ... AG8: =MAX(0,ABS(Statements!AF27-(Statements!AF24-Statements!AF26+Statements!AF25))-MAX(0.01,0.001*ABS(Statements!AF27)))
A9: opening[t] = closing[t-1], and opening[0] = 0 | B9: =MAX(D9:AG9) | C9: =IF(B9=0,"PASS","FAIL") | D9: =MAX(0,ABS(Statements!C24)-MAX(0.01,0.001*ABS(0))) | E9: =MAX(0,ABS(Statements!D24-Statements!C27)-MAX(0.01,0.001*ABS(Statements!D24))) | F9: =MAX(0,ABS(Statements!E24-Statements!D27)-MAX(0.01,0.001*ABS(Statements!E24))) | G9: =MAX(0,ABS(Statements!F24-Statements!E27)-MAX(0.01,0.001*ABS(Statements!F24))) | H9: =MAX(0,ABS(Statements!G24-Statements!F27)-MAX(0.01,0.001*ABS(Statements!G24))) | I9: =MAX(0,ABS(Statements!H24-Statements!G27)-MAX(0.01,0.001*ABS(Statements!H24))) | J9: =MAX(0,ABS(Statements!I24-Statements!H27)-MAX(0.01,0.001*ABS(Statements!I24))) | K9: =MAX(0,ABS(Statements!J24-Statements!I27)-MAX(0.01,0.001*ABS(Statements!J24))) | L9: =MAX(0,ABS(Statements!K24-Statements!J27)-MAX(0.01,0.001*ABS(Statements!K24))) | ... AG9: =MAX(0,ABS(Statements!AF24-Statements!AE27)-MAX(0.01,0.001*ABS(Statements!AF24)))
A10: ppe[t] = ppe[t-1] - depreciation[t] + capex[t] | B10: =MAX(D10:AG10) | C10: =IF(B10=0,"PASS","FAIL") | D10: =MAX(0,ABS(Statements!C29-(0-Statements!C9+Statements!C19))-MAX(0.01,0.001*ABS(Statements!C29))) | E10: =MAX(0,ABS(Statements!D29-(Statements!C29-Statements!D9+Statements!D19))-MAX(0.01,0.001*ABS(Statements!D29))) | F10: =MAX(0,ABS(Statements!E29-(Statements!D29-Statements!E9+Statements!E19))-MAX(0.01,0.001*ABS(Statements!E29))) | G10: =MAX(0,ABS(Statements!F29-(Statements!E29-Statements!F9+Statements!F19))-MAX(0.01,0.001*ABS(Statements!F29))) | H10: =MAX(0,ABS(Statements!G29-(Statements!F29-Statements!G9+Statements!G19))-MAX(0.01,0.001*ABS(Statements!G29))) | I10: =MAX(0,ABS(Statements!H29-(Statements!G29-Statements!H9+Statements!H19))-MAX(0.01,0.001*ABS(Statements!H29))) | J10: =MAX(0,ABS(Statements!I29-(Statements!H29-Statements!I9+Statements!I19))-MAX(0.01,0.001*ABS(Statements!I29))) | K10: =MAX(0,ABS(Statements!J29-(Statements!I29-Statements!J9+Statements!J19))-MAX(0.01,0.001*ABS(Statements!J29))) | L10: =MAX(0,ABS(Statements!K29-(Statements!J29-Statements!K9+Statements!K19))-MAX(0.01,0.001*ABS(Statements!K29))) | ... AG10: =MAX(0,ABS(Statements!AF29-(Statements!AE29-Statements!AF9+Statements!AF19))-MAX(0.01,0.001*ABS(Statements!AF29)))
A11: capex = debtDrawdown + equityDrawdown | B11: =MAX(D11:AG11) | C11: =IF(B11=0,"PASS","FAIL") | D11: =MAX(0,ABS(Statements!C19-(Statements!C20+Statements!C21))-MAX(0.01,0.001*ABS(Statements!C19))) | E11: =MAX(0,ABS(Statements!D19-(Statements!D20+Statements!D21))-MAX(0.01,0.001*ABS(Statements!D19))) | F11: =MAX(0,ABS(Statements!E19-(Statements!E20+Statements!E21))-MAX(0.01,0.001*ABS(Statements!E19))) | G11: =MAX(0,ABS(Statements!F19-(Statements!F20+Statements!F21))-MAX(0.01,0.001*ABS(Statements!F19))) | H11: =MAX(0,ABS(Statements!G19-(Statements!G20+Statements!G21))-MAX(0.01,0.001*ABS(Statements!G19))) | I11: =MAX(0,ABS(Statements!H19-(Statements!H20+Statements!H21))-MAX(0.01,0.001*ABS(Statements!H19))) | J11: =MAX(0,ABS(Statements!I19-(Statements!I20+Statements!I21))-MAX(0.01,0.001*ABS(Statements!I19))) | K11: =MAX(0,ABS(Statements!J19-(Statements!J20+Statements!J21))-MAX(0.01,0.001*ABS(Statements!J19))) | ... AG11: =MAX(0,ABS(Statements!AF19-(Statements!AF20+Statements!AF21))-MAX(0.01,0.001*ABS(Statements!AF19)))
A12: dscr is present exactly inside the debt life | B12: =MAX(D12:AG12) | C12: =IF(B12=0,"PASS","FAIL") | D12: =IF(AND(Statements!$C$1>=Identity!$B$13,Statements!$C$1<Identity!$B$13+Assumptions!$B$6)=(Statements!C31<>""),0,1) | E12: =IF(AND(Statements!$D$1>=Identity!$B$13,Statements!$D$1<Identity!$B$13+Assumptions!$B$6)=(Statements!D31<>""),0,1) | F12: =IF(AND(Statements!$E$1>=Identity!$B$13,Statements!$E$1<Identity!$B$13+Assumptions!$B$6)=(Statements!E31<>""),0,1) | G12: =IF(AND(Statements!$F$1>=Identity!$B$13,Statements!$F$1<Identity!$B$13+Assumptions!$B$6)=(Statements!F31<>""),0,1) | H12: =IF(AND(Statements!$G$1>=Identity!$B$13,Statements!$G$1<Identity!$B$13+Assumptions!$B$6)=(Statements!G31<>""),0,1) | I12: =IF(AND(Statements!$H$1>=Identity!$B$13,Statements!$H$1<Identity!$B$13+Assumptions!$B$6)=(Statements!H31<>""),0,1) | J12: =IF(AND(Statements!$I$1>=Identity!$B$13,Statements!$I$1<Identity!$B$13+Assumptions!$B$6)=(Statements!I31<>""),0,1) | K12: =IF(AND(Statements!$J$1>=Identity!$B$13,Statements!$J$1<Identity!$B$13+Assumptions!$B$6)=(Statements!J31<>""),0,1) | L12: =IF(AND(Statements!$K$1>=Identity!$B$13,Statements!$K$1<Identity!$B$13+Assumptions!$B$6)=(Statements!K31<>""),0,1) | M12: =IF(AND(Statements!$L$1>=Identity!$B$13,Statements!$L$1<Identity!$B$13+Assumptions!$B$6)=(Statements!L31<>""),0,1) | N12: =IF(AND(Statements!$M$1>=Identity!$B$13,Statements!$M$1<Identity!$B$13+Assumptions!$B$6)=(Statements!M31<>""),0,1) | O12: =IF(AND(Statements!$N$1>=Identity!$B$13,Statements!$N$1<Identity!$B$13+Assumptions!$B$6)=(Statements!N31<>""),0,1) | P12: =IF(AND(Statements!$O$1>=Identity!$B$13,Statements!$O$1<Identity!$B$13+Assumptions!$B$6)=(Statements!O31<>""),0,1) | Q12: =IF(AND(Statements!$P$1>=Identity!$B$13,Statements!$P$1<Identity!$B$13+Assumptions!$B$6)=(Statements!P31<>""),0,1) | R12: =IF(AND(Statements!$Q$1>=Identity!$B$13,Statements!$Q$1<Identity!$B$13+Assumptions!$B$6)=(Statements!Q31<>""),0,1) | S12: =IF(AND(Statements!$R$1>=Identity!$B$13,Statements!$R$1<Identity!$B$13+Assumptions!$B$6)=(Statements!R31<>""),0,1) | T12: =IF(AND(Statements!$S$1>=Identity!$B$13,Statements!$S$1<Identity!$B$13+Assumptions!$B$6)=(Statements!S31<>""),0,1) | U12: =IF(AND(Statements!$T$1>=Identity!$B$13,Statements!$T$1<Identity!$B$13+Assumptions!$B$6)=(Statements!T31<>""),0,1) | V12: =IF(AND(Statements!$U$1>=Identity!$B$13,Statements!$U$1<Identity!$B$13+Assumptions!$B$6)=(Statements!U31<>""),0,1) | W12: =IF(AND(Statements!$V$1>=Identity!$B$13,Statements!$V$1<Identity!$B$13+Assumptions!$B$6)=(Statements!V31<>""),0,1) | X12: =IF(AND(Statements!$W$1>=Identity!$B$13,Statements!$W$1<Identity!$B$13+Assumptions!$B$6)=(Statements!W31<>""),0,1) | Y12: =IF(AND(Statements!$X$1>=Identity!$B$13,Statements!$X$1<Identity!$B$13+Assumptions!$B$6)=(Statements!X31<>""),0,1) | Z12: =IF(AND(Statements!$Y$1>=Identity!$B$13,Statements!$Y$1<Identity!$B$13+Assumptions!$B$6)=(Statements!Y31<>""),0,1) | AA12: =IF(AND(Statements!$Z$1>=Identity!$B$13,Statements!$Z$1<Identity!$B$13+Assumptions!$B$6)=(Statements!Z31<>""),0,1) | AB12: =IF(AND(Statements!$AA$1>=Identity!$B$13,Statements!$AA$1<Identity!$B$13+Assumptions!$B$6)=(Statements!AA31<>""),0,1) | AC12: =IF(AND(Statements!$AB$1>=Identity!$B$13,Statements!$AB$1<Identity!$B$13+Assumptions!$B$6)=(Statements!AB31<>""),0,1) | AD12: =IF(AND(Statements!$AC$1>=Identity!$B$13,Statements!$AC$1<Identity!$B$13+Assumptions!$B$6)=(Statements!AC31<>""),0,1) | AE12: =IF(AND(Statements!$AD$1>=Identity!$B$13,Statements!$AD$1<Identity!$B$13+Assumptions!$B$6)=(Statements!AD31<>""),0,1) | AF12: =IF(AND(Statements!$AE$1>=Identity!$B$13,Statements!$AE$1<Identity!$B$13+Assumptions!$B$6)=(Statements!AE31<>""),0,1) | AG12: =IF(AND(Statements!$AF$1>=Identity!$B$13,Statements!$AF$1<Identity!$B$13+Assumptions!$B$6)=(Statements!AF31<>""),0,1)
A13: dscr = ebitda / (interestPaid + debtRepayment) | B13: =MAX(D13:AG13) | C13: =IF(B13=0,"PASS","FAIL") | D13: =IF(OR(Statements!C31="",Statements!C16+Statements!C17=0),0,MAX(0,ABS(Statements!C31-Statements!C8/(Statements!C16+Statements!C17))-MAX(0.001,0.001*ABS(Statements!C31)))) | E13: =IF(OR(Statements!D31="",Statements!D16+Statements!D17=0),0,MAX(0,ABS(Statements!D31-Statements!D8/(Statements!D16+Statements!D17))-MAX(0.001,0.001*ABS(Statements!D31)))) | F13: =IF(OR(Statements!E31="",Statements!E16+Statements!E17=0),0,MAX(0,ABS(Statements!E31-Statements!E8/(Statements!E16+Statements!E17))-MAX(0.001,0.001*ABS(Statements!E31)))) | G13: =IF(OR(Statements!F31="",Statements!F16+Statements!F17=0),0,MAX(0,ABS(Statements!F31-Statements!F8/(Statements!F16+Statements!F17))-MAX(0.001,0.001*ABS(Statements!F31)))) | H13: =IF(OR(Statements!G31="",Statements!G16+Statements!G17=0),0,MAX(0,ABS(Statements!G31-Statements!G8/(Statements!G16+Statements!G17))-MAX(0.001,0.001*ABS(Statements!G31)))) | I13: =IF(OR(Statements!H31="",Statements!H16+Statements!H17=0),0,MAX(0,ABS(Statements!H31-Statements!H8/(Statements!H16+Statements!H17))-MAX(0.001,0.001*ABS(Statements!H31)))) | J13: =IF(OR(Statements!I31="",Statements!I16+Statements!I17=0),0,MAX(0,ABS(Statements!I31-Statements!I8/(Statements!I16+Statements!I17))-MAX(0.001,0.001*ABS(Statements!I31)))) | K13: =IF(OR(Statements!J31="",Statements!J16+Statements!J17=0),0,MAX(0,ABS(Statements!J31-Statements!J8/(Statements!J16+Statements!J17))-MAX(0.001,0.001*ABS(Statements!J31)))) | ... AG13: =IF(OR(Statements!AF31="",Statements!AF16+Statements!AF17=0),0,MAX(0,ABS(Statements!AF31-Statements!AF8/(Statements!AF16+Statements!AF17))-MAX(0.001,0.001*ABS(Statements!AF31))))
A14: closing[last] = 0 | B14: =MAX(0,ABS(Statements!AF27)-MAX(0.01,0.001*ABS(0))) | C14: =IF(B14=0,"PASS","FAIL")
A15: sum debtDrawdown = seniorDebt | B15: =MAX(0,ABS(SUM(Statements!$C$20:$AF$20)-Identity!$B$26)-MAX(0.01,0.001*ABS(Identity!$B$26))) | C15: =IF(B15=0,"PASS","FAIL")
A16: sum equityDrawdown = totalCapex - seniorDebt | B16: =MAX(0,ABS(SUM(Statements!$C$21:$AF$21)-(Identity!$B$25-Identity!$B$26))-MAX(0.01,0.001*ABS(Identity!$B$25-Identity!$B$26))) | C16: =IF(B16=0,"PASS","FAIL")
A17: sum capex = totalCapex | B17: =MAX(0,ABS(SUM(Statements!$C$19:$AF$19)-Identity!$B$25)-MAX(0.01,0.001*ABS(Identity!$B$25))) | C17: =IF(B17=0,"PASS","FAIL")
A18: sum depreciation = totalCapex - ppe[last] | B18: =MAX(0,ABS(SUM(Statements!$C$9:$AF$9)-(Identity!$B$25-Statements!AF29))-MAX(0.01,0.001*ABS(Identity!$B$25))) | C18: =IF(B18=0,"PASS","FAIL")
A19: taxExpense = taxRate * max(0, pbt) [warn] | B19: =MAX(0,ABS(SUM(Statements!$C$13:$AF$13)-Assumptions!$B$3*SUMPRODUCT((Statements!$C$12:$AF$12>0)*Statements!$C$12:$AF$12))-MAX(0.01,0.001*ABS(SUM(Statements!$C$13:$AF$13)))) | C19: =IF(B19=0,"PASS","FAIL")
A21: Live formulas against Statements, Identity and Assumptions. Each cell holds the BREACH over tolerance -- max(0, |residual| - max(absolute, 0.1% of the line)) -- so zero means the year is inside tolerance and any non-zero cell names the year that is not. The absolute limb is EUR 0.01m for a money line and 0.001 for the DSCR ratio, from the assumption set. Every check must read PASS before the file is loaded; the last one is a plausibility warning, not a blocker.
